{
  "scaleLevel": {
    "en": "nominal",
    "de": "nominal"
  },
  "label": {
    "en": "additional benefits last job: relevantly salary elements, namely",
    "de": "letzte Stelle zus채tzl. Gehaltsbestandteile: s채chliche, und zwar"
  },
  "derivedVariablesIdentifier": null,
  "doNotDisplayThousandsSeparator": false,
  "dataType": {
    "en": "numeric",
    "de": "numerisch"
  },
  "filterDetails": {
    "expression": "if inlist(aocc19,-998,1,2)",
    "description": {
      "en": null,
      "de": null
    },
    "expressionLanguage": "Stata"
  },
  "panelIdentifier": "gra2009-ds1-occ332f_g1",
  "accessWays": ["remote-desktop-suf", "onsite-suf"],
  "surveyNumbers": [1],
  "indexInDataSet": 697,
  "generationDetails": {
    "description": {
      "en": null,
      "de": "Es wurden keine offenen Angaben gemacht oder die offenen Angaben wurden nicht vercodet. Daher enth채lt diese Variable nur Missings."
    },
    "rule": null,
    "ruleExpressionLanguage": null
  },
  "storageType": "integer",
  "distribution": {
    "totalValidRelativeFrequency": 0,
    "statistics": null,
    "totalAbsoluteFrequency": 10494,
    "validResponses": null,
    "totalValidAbsoluteFrequency": 0,
    "missings": [
      {
        "absoluteFrequency": 2401,
        "label": {
          "en": "no answer",
          "de": "keine Angabe"
        },
        "relativeFrequency": 22.88,
        "code": -998
      },
      {
        "absoluteFrequency": 2088,
        "label": {
          "en": "filtered",
          "de": "filterbedingt fehlend"
        },
        "relativeFrequency": 19.9,
        "code": -989
      },
      {
        "absoluteFrequency": 6005,
        "label": {
          "en": "does not apply",
          "de": "trifft nicht zu"
        },
        "relativeFrequency": 57.22,
        "code": -988
      }
    ]
  },
  "relatedQuestions": [
    {
      "instrumentNumber": 1,
      "questionNumber": "5.13",
      "relatedQuestionStrings": {
        "en": null,
        "de": "Welche zus채tzlichen (Brutto-)Gehaltsbestandteile bekommen Sie?"
      }
    }
  ],
  "relatedVariables": null,
  "annotations": {
    "en": null,
    "de": null
  }
}
