{
  "scaleLevel": {
    "en": "nominal",
    "de": "nominal"
  },
  "label": {
    "en": "6th job: type of employment",
    "de": "6. Tätigkeit: Art des Arbeitsverhältnisses"
  },
  "derivedVariablesIdentifier": null,
  "doNotDisplayThousandsSeparator": false,
  "dataType": {
    "en": "numeric",
    "de": "numerisch"
  },
  "filterDetails": {
    "expression": "if inlist(aocc19,-998,1,2)",
    "description": {
      "en": null,
      "de": null
    },
    "expressionLanguage": "Stata"
  },
  "panelIdentifier": "gra2009-ds1-occ246f",
  "accessWays": ["download-cuf", "download-suf", "remote-desktop-suf", "onsite-suf"],
  "surveyNumbers": [1],
  "indexInDataSet": 594,
  "generationDetails": {
    "description": {
      "en": null,
      "de": null
    },
    "rule": null,
    "ruleExpressionLanguage": null
  },
  "storageType": "integer",
  "distribution": {
    "totalValidRelativeFrequency": 0.19,
    "statistics": {
      "deviance": "2.374566",
      "mode": "2"
    },
    "totalAbsoluteFrequency": 10494,
    "validResponses": [
      {
        "absoluteFrequency": 2,
        "label": {
          "en": "Unlimited",
          "de": "unbefristet"
        },
        "relativeFrequency": 0.02,
        "validRelativeFrequency": 10,
        "value": "1"
      },
      {
        "absoluteFrequency": 9,
        "label": {
          "en": "Limited (fixed-term contract)",
          "de": "befristet (Zeitvertrag)"
        },
        "relativeFrequency": 0.09,
        "validRelativeFrequency": 45,
        "value": "2"
      },
      {
        "absoluteFrequency": 2,
        "label": {
          "en": "Apprenticeship",
          "de": "Ausbildungsverhältnis"
        },
        "relativeFrequency": 0.02,
        "validRelativeFrequency": 10,
        "value": "4"
      },
      {
        "absoluteFrequency": 7,
        "label": {
          "en": "Fee/works contract",
          "de": "Honorar-/Werkvertrag"
        },
        "relativeFrequency": 0.07,
        "validRelativeFrequency": 35,
        "value": "5"
      }
    ],
    "totalValidAbsoluteFrequency": 20,
    "missings": [
      {
        "absoluteFrequency": 8386,
        "label": {
          "en": "no answer",
          "de": "keine Angabe"
        },
        "relativeFrequency": 79.91,
        "code": -998
      },
      {
        "absoluteFrequency": 2088,
        "label": {
          "en": "filtered",
          "de": "filterbedingt fehlend"
        },
        "relativeFrequency": 19.9,
        "code": -989
      }
    ]
  },
  "relatedQuestions": [
    {
      "instrumentNumber": 1,
      "questionNumber": "5.4",
      "relatedQuestionStrings": {
        "en": null,
        "de": "Im Folgenden bitten wir Sie um eine Beschreibung der verschiedenen beruflichen Tätigkeiten, die Sie seit Ihrem Studienabschluss ausgeübt haben."
      }
    }
  ],
  "relatedVariables": null,
  "annotations": {
    "en": null,
    "de": null
  }
}
