{
  "scaleLevel": {
    "en": "ordinal",
    "de": "ordinal"
  },
  "label": {
    "en": "course of study: discussion of exam performance",
    "de": "Studium: Besprechung Prüfungsleistungen"
  },
  "derivedVariablesIdentifier": null,
  "doNotDisplayThousandsSeparator": false,
  "dataType": {
    "en": "numeric",
    "de": "numerisch"
  },
  "filterDetails": {
    "expression": null,
    "description": {
      "en": null,
      "de": null
    },
    "expressionLanguage": null
  },
  "panelIdentifier": null,
  "accessWays": ["download-cuf", "download-suf", "remote-desktop-suf", "onsite-suf"],
  "surveyNumbers": [1],
  "indexInDataSet": 221,
  "generationDetails": {
    "description": {
      "en": null,
      "de": null
    },
    "rule": null,
    "ruleExpressionLanguage": null
  },
  "storageType": "integer",
  "distribution": {
    "totalValidRelativeFrequency": 99.25,
    "statistics": {
      "firstQuartile": "2",
      "deviance": "2.983367",
      "highWhisker": 5,
      "lowWhisker": 1,
      "minimum": "1",
      "thirdQuartile": "4",
      "meanDeviation": "1533.008",
      "maximum": "5",
      "mode": "3",
      "median": "3"
    },
    "totalAbsoluteFrequency": 10494,
    "validResponses": [
      {
        "absoluteFrequency": 1041,
        "label": {
          "en": "Very good",
          "de": "sehr gut"
        },
        "relativeFrequency": 9.92,
        "validRelativeFrequency": 10,
        "value": "1"
      },
      {
        "absoluteFrequency": 3123,
        "label": {
          "en": "2 ",
          "de": "2 "
        },
        "relativeFrequency": 29.76,
        "validRelativeFrequency": 29.99,
        "value": "2"
      },
      {
        "absoluteFrequency": 3192,
        "label": {
          "en": "3 ",
          "de": "3 "
        },
        "relativeFrequency": 30.42,
        "validRelativeFrequency": 30.65,
        "value": "3"
      },
      {
        "absoluteFrequency": 2158,
        "label": {
          "en": "4 ",
          "de": "4 "
        },
        "relativeFrequency": 20.56,
        "validRelativeFrequency": 20.72,
        "value": "4"
      },
      {
        "absoluteFrequency": 901,
        "label": {
          "en": "Very bad",
          "de": "sehr schlecht"
        },
        "relativeFrequency": 8.59,
        "validRelativeFrequency": 8.65,
        "value": "5"
      }
    ],
    "totalValidAbsoluteFrequency": 10415,
    "missings": [
      {
        "absoluteFrequency": 79,
        "label": {
          "en": "no answer",
          "de": "keine Angabe"
        },
        "relativeFrequency": 0.75,
        "code": -998
      }
    ]
  },
  "relatedQuestions": [
    {
      "instrumentNumber": 1,
      "questionNumber": "1.15",
      "relatedQuestionStrings": {
        "en": null,
        "de": "Wie beurteilen Sie die folgenden Aspekte Ihres abgeschlossenen Studiums?"
      }
    }
  ],
  "relatedVariables": null,
  "annotations": {
    "en": null,
    "de": null
  }
}
