{
  "relatedQuestions": [
    {
      "relatedQuestionStrings": {
        "en": null,
        "de": "Bitte tragen Sie diese längerfristigen Studienangebote, die Sie nach Ihrem Studienabschluss aus dem Jahr 2008/2009 begonnen, weitergeführt oder abgeschlossen haben (auch abgebrochene oder unterbrochene), in das folgende Tableau ein!"
      },
      "questionNumber": "5.2",
      "instrumentNumber": 2
    }
  ],
  "distribution": {
    "statistics": {
      "meanDeviation": null,
      "mode": null,
      "highWhisker": null,
      "lowWhisker": null,
      "thirdQuartile": null,
      "firstQuartile": null,
      "standardDeviation": null,
      "median": null,
      "kurtosis": null,
      "skewness": null,
      "maximum": null,
      "minimum": null,
      "meanValue": null
    },
    "missings": [
      {
        "label": {
          "en": "no answer",
          "de": "keine Angabe"
        },
        "relativeFrequency": 19.94,
        "absoluteFrequency": 2093,
        "code": -998
      },
      {
        "label": {
          "en": "not participated (panel)",
          "de": "keine Teilnahme (Panel)"
        },
        "relativeFrequency": 54.69,
        "absoluteFrequency": 5739,
        "code": -995
      },
      {
        "label": {
          "en": "filtered",
          "de": "filterbedingt fehlend"
        },
        "relativeFrequency": 25.37,
        "absoluteFrequency": 2662,
        "code": -989
      }
    ],
    "validResponses": null,
    "totalValidRelativeFrequency": 0,
    "totalValidAbsoluteFrequency": 0,
    "totalAbsoluteFrequency": 10494
  },
  "filterDetails": {
    "expressionLanguage": "Stata",
    "description": {
      "en": null,
      "de": null
    },
    "expression": "if inlist(bfec14,1,-998)"
  },
  "generationDetails": {
    "ruleExpressionLanguage": null,
    "rule": null,
    "description": {
      "en": null,
      "de": "Diese Variable wurde zum Zweck der Anonymisierung durch Aggregation aus den codierten Fächerangaben generiert. Zur Aggregation wurde die Zuordnung der Destatis Fächersystematik (WiSe 2008/09) (vgl. cl-destatis-studienfach-2009) verwendet. Für die Zuordnung des darin nicht enthaltenen Fächercodes 310 (\"Regenerative Energien\" --> Studienbereich: \"Ingenieurwesen allgemein\") wurde das Schlüsselverzeichnis 2012/2013 (Code 61) herangezogen."
    }
  },
  "storageType": "integer",
  "relatedVariables": null,
  "doNotDisplayThousandsSeparator": false,
  "derivedVariablesIdentifier": "gra2009-ds1-bfec155g",
  "panelIdentifier": null,
  "surveyNumbers": [2],
  "indexInDataSet": 1263,
  "accessWays": ["download-suf", "remote-desktop-suf", "onsite-suf"],
  "annotations": {
    "en": null,
    "de": null
  },
  "label": {
    "en": "5th further acad. qualification: subject (area of study)",
    "de": "5. weitere akad. Qualifikation: Studienfach (Studienbereiche)"
  },
  "scaleLevel": {
    "en": "nominal",
    "de": "nominal"
  },
  "dataType": {
    "en": "numeric",
    "de": "numerisch"
  }
}
