{
  "scaleLevel": {
    "en": "ordinal",
    "de": "ordinal"
  },
  "label": {
    "en": "moving (other town): better leisure opportunities",
    "de": "Umzug (Stadtwechsel): bessere Freizeitmöglichkeiten"
  },
  "derivedVariablesIdentifier": null,
  "doNotDisplayThousandsSeparator": false,
  "dataType": {
    "en": "numeric",
    "de": "numerisch"
  },
  "filterDetails": {
    "expression": null,
    "description": {
      "en": null,
      "de": null
    },
    "expressionLanguage": null
  },
  "panelIdentifier": null,
  "accessWays": ["download-cuf", "download-suf", "remote-desktop-suf", "onsite-suf"],
  "surveyNumbers": [4],
  "indexInDataSet": 1535,
  "generationDetails": {
    "description": {
      "en": null,
      "de": null
    },
    "rule": null,
    "ruleExpressionLanguage": null
  },
  "storageType": "integer",
  "distribution": {
    "totalValidRelativeFrequency": 23.04,
    "statistics": {
      "firstQuartile": "3",
      "deviance": "2.994633",
      "highWhisker": 5,
      "lowWhisker": 1,
      "minimum": "1",
      "thirdQuartile": "5",
      "meanDeviation": "99.3342",
      "maximum": "5",
      "mode": "5",
      "median": "4"
    },
    "totalAbsoluteFrequency": 10494,
    "validResponses": [
      {
        "absoluteFrequency": 149,
        "label": {
          "en": "I agree",
          "de": "stimme sehr zu"
        },
        "relativeFrequency": 1.42,
        "validRelativeFrequency": 6.16,
        "value": "1"
      },
      {
        "absoluteFrequency": 318,
        "label": {
          "en": "2",
          "de": "2"
        },
        "relativeFrequency": 3.03,
        "validRelativeFrequency": 13.15,
        "value": "2"
      },
      {
        "absoluteFrequency": 611,
        "label": {
          "en": "3",
          "de": "3"
        },
        "relativeFrequency": 5.82,
        "validRelativeFrequency": 25.27,
        "value": "3"
      },
      {
        "absoluteFrequency": 662,
        "label": {
          "en": "4",
          "de": "4"
        },
        "relativeFrequency": 6.31,
        "validRelativeFrequency": 27.38,
        "value": "4"
      },
      {
        "absoluteFrequency": 678,
        "label": {
          "en": "I do not agree at all",
          "de": "stimme überhaupt nicht zu"
        },
        "relativeFrequency": 6.46,
        "validRelativeFrequency": 28.04,
        "value": "5"
      }
    ],
    "totalValidAbsoluteFrequency": 2418,
    "missings": [
      {
        "absoluteFrequency": 47,
        "label": {
          "en": "no answer",
          "de": "keine Angabe"
        },
        "relativeFrequency": 0.45,
        "code": -998
      },
      {
        "absoluteFrequency": 8029,
        "label": {
          "en": "not participated (panel)",
          "de": "keine Teilnahme (Panel)"
        },
        "relativeFrequency": 76.51,
        "code": -995
      }
    ]
  },
  "relatedQuestions": [
    {
      "instrumentNumber": 5,
      "questionNumber": "04",
      "relatedQuestionStrings": {
        "en": null,
        "de": null
      }
    }
  ],
  "relatedVariables": null,
  "annotations": {
    "en": null,
    "de": null
  }
}
