{
  "scaleLevel": {
    "en": "nominal",
    "de": "nominal"
  },
  "label": {
    "en": "3rd apartment: main/second apartment",
    "de": "3. Wohnung: Haupt-/Zweitwohnung"
  },
  "derivedVariablesIdentifier": null,
  "doNotDisplayThousandsSeparator": false,
  "dataType": {
    "en": "numeric",
    "de": "numerisch"
  },
  "filterDetails": {
    "expression": "if inlist(mres021,1,-998) & mres031==1 & mres041==1",
    "description": {
      "en": null,
      "de": null
    },
    "expressionLanguage": "Stata"
  },
  "panelIdentifier": null,
  "accessWays": ["download-cuf", "download-suf", "remote-desktop-suf", "onsite-suf"],
  "surveyNumbers": [4],
  "indexInDataSet": 1655,
  "generationDetails": {
    "description": {
      "en": null,
      "de": null
    },
    "rule": null,
    "ruleExpressionLanguage": null
  },
  "storageType": "integer",
  "distribution": {
    "totalValidRelativeFrequency": 5.69,
    "statistics": {
      "deviance": "1.080189",
      "mode": "1"
    },
    "totalAbsoluteFrequency": 10494,
    "validResponses": [
      {
        "absoluteFrequency": 505,
        "label": {
          "en": "The main apartment",
          "de": "Hauptwohnung"
        },
        "relativeFrequency": 4.81,
        "validRelativeFrequency": 84.59,
        "value": "1"
      },
      {
        "absoluteFrequency": 69,
        "label": {
          "en": "Second apartment for professional reasons",
          "de": "Zweitwohnung aus beruflichen Gründen"
        },
        "relativeFrequency": 0.66,
        "validRelativeFrequency": 11.56,
        "value": "2"
      },
      {
        "absoluteFrequency": 16,
        "label": {
          "en": "Second apartment for other reasons",
          "de": "Zweitwohnung aus sonstigen Gründen"
        },
        "relativeFrequency": 0.15,
        "validRelativeFrequency": 2.68,
        "value": "3"
      },
      {
        "absoluteFrequency": 7,
        "label": {
          "en": "50-50",
          "de": "teils, teils"
        },
        "relativeFrequency": 0.07,
        "validRelativeFrequency": 1.17,
        "value": "4"
      }
    ],
    "totalValidAbsoluteFrequency": 597,
    "missings": [
      {
        "absoluteFrequency": 64,
        "label": {
          "en": "no answer",
          "de": "keine Angabe"
        },
        "relativeFrequency": 0.61,
        "code": -998
      },
      {
        "absoluteFrequency": 8029,
        "label": {
          "en": "not participated (panel)",
          "de": "keine Teilnahme (Panel)"
        },
        "relativeFrequency": 76.51,
        "code": -995
      },
      {
        "absoluteFrequency": 1804,
        "label": {
          "en": "filtered",
          "de": "filterbedingt fehlend"
        },
        "relativeFrequency": 17.19,
        "code": -989
      }
    ]
  },
  "relatedQuestions": [
    {
      "instrumentNumber": 5,
      "questionNumber": "14.1",
      "relatedQuestionStrings": {
        "en": null,
        "de": null
      }
    }
  ],
  "relatedVariables": null,
  "annotations": {
    "en": null,
    "de": null
  }
}
