{
  "relatedQuestions": [
    {
      "relatedQuestionStrings": {
        "en": null,
        "de": "Aus welchem Grund haben Sie diese Wohnung wieder aufgegeben?,Aus beruflichen Gr체nden,Aus privaten Gr체nden,Aufgrund der Wohnsituation,Um n채her zu Verwandten zu ziehen"
      },
      "questionNumber": "12",
      "instrumentNumber": 5
    }
  ],
  "distribution": {
    "statistics": {
      "meanDeviation": null,
      "mode": "0",
      "highWhisker": null,
      "lowWhisker": null,
      "thirdQuartile": null,
      "firstQuartile": null,
      "standardDeviation": null,
      "median": null,
      "kurtosis": null,
      "skewness": null,
      "maximum": null,
      "minimum": null,
      "meanValue": null
    },
    "missings": [
      {
        "label": {
          "en": "no answer",
          "de": "keine Angabe"
        },
        "relativeFrequency": 0.02,
        "absoluteFrequency": 2,
        "code": -998
      },
      {
        "label": {
          "en": "not participated (panel)",
          "de": "keine Teilnahme (Panel)"
        },
        "relativeFrequency": 76.51,
        "absoluteFrequency": 8029,
        "code": -995
      },
      {
        "label": {
          "en": "filtered",
          "de": "filterbedingt fehlend"
        },
        "relativeFrequency": 17,
        "absoluteFrequency": 1784,
        "code": -989
      }
    ],
    "validResponses": [
      {
        "label": {
          "en": "Not stated",
          "de": "nicht genannt"
        },
        "validRelativeFrequency": 94.26,
        "relativeFrequency": 6.1,
        "absoluteFrequency": 640,
        "value": "0"
      },
      {
        "label": {
          "en": "Stated",
          "de": "genannt"
        },
        "validRelativeFrequency": 5.74,
        "relativeFrequency": 0.37,
        "absoluteFrequency": 39,
        "value": "1"
      }
    ],
    "totalValidRelativeFrequency": 6.47,
    "totalValidAbsoluteFrequency": 679,
    "totalAbsoluteFrequency": 10494
  },
  "filterDetails": {
    "expressionLanguage": "Stata",
    "description": {
      "en": null,
      "de": null
    },
    "expression": "if inlist(mres021,1,-998) & mres031==1 & mres033==2"
  },
  "generationDetails": {
    "ruleExpressionLanguage": null,
    "rule": null,
    "description": {
      "en": null,
      "de": null
    }
  },
  "storageType": "integer",
  "relatedVariables": null,
  "doNotDisplayThousandsSeparator": false,
  "derivedVariablesIdentifier": null,
  "panelIdentifier": null,
  "surveyNumbers": [4],
  "indexInDataSet": 1629,
  "accessWays": ["download-cuf", "download-suf", "remote-desktop-suf", "onsite-suf"],
  "annotations": {
    "en": null,
    "de": null
  },
  "label": {
    "en": "reason for leaving 2nd apartment (private): proximity to relatives",
    "de": "Grund Aufgabe 2. Wohnung (privat): N채he zu Verwandten"
  },
  "scaleLevel": {
    "en": "nominal",
    "de": "nominal"
  },
  "dataType": {
    "en": "numeric",
    "de": "numerisch"
  }
}
