{
	"surveyNumbers" : [
		1
	],
	"dataType" : {
		"de" : "numerisch",
		"en" : "numeric"
	},
	"scaleLevel" : {
		"de" : "ordinal",
		"en" : "ordinal"
	},
	"label" : {
		"de" : "wichtig für Beruf: interkulturelles Verständnis",
		"en" : null
	},
	"relatedQuestions" : [
		{
			"instrumentNumber" : 1,
			"questionNumber" : "1.19",
			"relatedQuestionStrings" : {
				"de" : "Wie wichtig sind die folgenden Kenntnisse und Fähigkeiten für Ihre derzeitige (bzw., wenn Sie nicht berufstätig sind, voraussichtliche) berufliche Tätigkeit (linke Spalte)? In welchem Maße verfügten Sie bei Abschluss des Erststudiums über  diese Kenntnisse und Fähigkeiten (rechte Spalte)?",
				"en" : null
			}
		}
	],
	"indexInDataSet" : 267,
	"distribution" : {
		"totalAbsoluteFrequency" : 10494,
		"totalValidAbsoluteFrequency" : 10135,
		"totalValidRelativeFrequency" : 96.58,
		"histogram" : {
			"numberOfBins" : null,
			"start" : null,
			"end" : null
		},
		"statistics" : {
			"meanValue" : null,
			"minimum" : "1",
			"maximum" : "5",
			"skewness" : null,
			"kurtosis" : null,
			"median" : "3",
			"mode" : "3",
			"standardDeviation" : null,
			"deviance" : "3.18536750899543",
			"meanDeviation" : "298.0026",
			"firstQuartile" : "2",
			"thirdQuartile" : "4",
			"lowWhisker" : 1,
			"highWhisker" : 5
		},
		"missings" : [
			{
				"code" : -998,
				"label" : {
					"de" : "keine Angabe",
					"en" : null
				},
				"relativeFrequency" : 3.42,
				"absoluteFrequency" : 359
			}
		],
		"validResponses" : [
			{
				"value" : "1",
				"label" : {
					"de" : "sehr wichtig",
					"en" : null
				},
				"relativeFrequency" : 18.49,
				"absoluteFrequency" : 1940,
				"validRelativeFrequency" : 19.14
			},
			{
				"value" : "2",
				"label" : {
					"de" : "2",
					"en" : null
				},
				"relativeFrequency" : 21.56,
				"absoluteFrequency" : 2262,
				"validRelativeFrequency" : 22.32
			},
			{
				"value" : "3",
				"label" : {
					"de" : "3",
					"en" : null
				},
				"relativeFrequency" : 23.56,
				"absoluteFrequency" : 2472,
				"validRelativeFrequency" : 24.39
			},
			{
				"value" : "4",
				"label" : {
					"de" : "4",
					"en" : null
				},
				"relativeFrequency" : 19.64,
				"absoluteFrequency" : 2061,
				"validRelativeFrequency" : 20.34
			},
			{
				"value" : "5",
				"label" : {
					"de" : "unwichtig",
					"en" : null
				},
				"relativeFrequency" : 13.34,
				"absoluteFrequency" : 1400,
				"validRelativeFrequency" : 13.81
			}
		]
	}
}