{
	"surveyNumbers" : [
		2
	],
	"dataType" : {
		"de" : "numerisch",
		"en" : "numeric"
	},
	"scaleLevel" : {
		"de" : "ordinal",
		"en" : "ordinal"
	},
	"label" : {
		"de" : "Arbeitsform: Kunden gelten als Partner",
		"en" : "type of work: customer regarded as partner"
	},
	"relatedQuestions" : [
		{
			"instrumentNumber" : 3,
			"questionNumber" : "39",
			"relatedQuestionStrings" : {
				"de" : null,
				"en" : null
			}
		},
		{
			"instrumentNumber" : 2,
			"questionNumber" : "4.23",
			"relatedQuestionStrings" : {
				"de" : "Wie würden Sie Ihren Arbeitsplatz, Ihre Arbeitsbedingungen und Ihre Arbeitsumgebung beschreiben?",
				"en" : null
			}
		}
	],
	"distribution" : {
		"totalAbsoluteFrequency" : 10494,
		"totalValidAbsoluteFrequency" : 4531,
		"totalValidRelativeFrequency" : 43.18,
		"histogram" : {
			"numberOfBins" : null,
			"start" : null,
			"end" : null
		},
		"statistics" : {
			"meanValue" : null,
			"minimum" : "1",
			"maximum" : "5",
			"skewness" : null,
			"kurtosis" : null,
			"median" : "3",
			"mode" : "3",
			"standardDeviation" : null,
			"deviance" : "3.10782966134618",
			"meanDeviation" : "197.1858",
			"firstQuartile" : "2",
			"thirdQuartile" : "4",
			"lowWhisker" : 1,
			"highWhisker" : 5
		},
		"missings" : [
			{
				"code" : -998,
				"label" : {
					"de" : "keine Angabe",
					"en" : "no answer"
				},
				"relativeFrequency" : 1.84,
				"absoluteFrequency" : 193
			},
			{
				"code" : -995,
				"label" : {
					"de" : "keine Teilnahme (Panel)",
					"en" : "not participated (panel)"
				},
				"relativeFrequency" : 54.69,
				"absoluteFrequency" : 5739
			},
			{
				"code" : -989,
				"label" : {
					"de" : "filterbedingt fehlend",
					"en" : "filtered"
				},
				"relativeFrequency" : 0.3,
				"absoluteFrequency" : 31
			}
		],
		"validResponses" : [
			{
				"value" : "1",
				"label" : {
					"de" : "trifft sehr stark zu",
					"en" : "Very strong"
				},
				"relativeFrequency" : 5.77,
				"absoluteFrequency" : 605,
				"validRelativeFrequency" : 13.35
			},
			{
				"value" : "2",
				"label" : {
					"de" : "2",
					"en" : "2 "
				},
				"relativeFrequency" : 12.07,
				"absoluteFrequency" : 1267,
				"validRelativeFrequency" : 27.96
			},
			{
				"value" : "3",
				"label" : {
					"de" : "3",
					"en" : "3 "
				},
				"relativeFrequency" : 12.24,
				"absoluteFrequency" : 1284,
				"validRelativeFrequency" : 28.34
			},
			{
				"value" : "4",
				"label" : {
					"de" : "4",
					"en" : "4 "
				},
				"relativeFrequency" : 7.03,
				"absoluteFrequency" : 738,
				"validRelativeFrequency" : 16.29
			},
			{
				"value" : "5",
				"label" : {
					"de" : "trifft gar nicht zu",
					"en" : "Not at all"
				},
				"relativeFrequency" : 6.07,
				"absoluteFrequency" : 637,
				"validRelativeFrequency" : 14.06
			}
		]
	}
}